thorndyke/__init__.py
thorndyke/banner.py
thorndyke/colors.py
thorndyke/default_lookup.py
thorndyke/found.py
thorndyke/headers.py
thorndyke/main.py
thorndyke/not_found.py
thorndyke/sites.py
thorndyke-2022.1.2.1.dist-info/LICENSE
thorndyke-2022.1.2.1.dist-info/METADATA
thorndyke-2022.1.2.1.dist-info/WHEEL
thorndyke-2022.1.2.1.dist-info/entry_points.txt
thorndyke-2022.1.2.1.dist-info/top_level.txt
thorndyke-2022.1.2.1.dist-info/RECORD
