Metadata-Version: 2.1
Name: thorndyke
Version: 2022.1.2.1
Summary: Lightweight username enumeration tool
Home-page: https://github.com/rlyonheart/thorndyke
Author: Richard Mwewa
Author-email: richardmwewa@duck.com
License: GNU General Public License v3 (GPLv3)
Platform: UNKNOWN
Classifier: Intended Audience :: Information Technology
Classifier: License :: OSI Approved :: GNU General Public License v3 (GPLv3)
Classifier: Operating System :: POSIX :: Linux
Classifier: Natural Language :: English
Classifier: Programming Language :: Python :: 3
License-File: LICENSE
Requires-Dist: requests
Requires-Dist: tqdm
